{"_type":"export","__export_format":4,"__export_date":"2024-11-29T14:38:51.085Z","__export_source":"insomnia.desktop.app:v10.2.0","resources":[{"_id":"req_3df715829582457a93750e35dd6a11f7","parentId":"wrk_f646fb5ab48c4a0dbb096aa3f51983cc","modified":1732890224968,"created":1732890210895,"url":"http://localhost:8080/ads","name":"Pegar todos os Anuncios","description":"","method":"GET","body":{},"parameters":[],"headers":[{"name":"User-Agent","value":"insomnia/10.2.0"}],"authentication":{},"metaSortKey":-1732890210895,"isPrivate":false,"pathParameters":[],"settingStoreCookies":true,"settingSendCookies":true,"settingDisableRenderRequestBody":false,"settingEncodeUrl":true,"settingRebuildPath":true,"settingFollowRedirects":"global","_type":"request"},{"_id":"wrk_f646fb5ab48c4a0dbb096aa3f51983cc","parentId":null,"modified":1731812601515,"created":1731812601515,"name":"LinkBaby","description":"","scope":"collection","_type":"workspace"},{"_id":"req_a366ba9cf8794b359f64481f8efd0b1e","parentId":"wrk_f646fb5ab48c4a0dbb096aa3f51983cc","modified":1732889973823,"created":1732889929181,"url":"http://localhost:8080/ad?email=ana.souza@example.com","name":"Pegar Anuncio","description":"","method":"GET","body":{},"parameters":[],"headers":[{"name":"User-Agent","value":"insomnia/10.2.0"}],"authentication":{},"metaSortKey":-1732889929181,"isPrivate":false,"pathParameters":[],"settingStoreCookies":true,"settingSendCookies":true,"settingDisableRenderRequestBody":false,"settingEncodeUrl":true,"settingRebuildPath":true,"settingFollowRedirects":"global","_type":"request"},{"_id":"req_ed7d3aaaea4947088bb24e2da473cbaa","parentId":"wrk_f646fb5ab48c4a0dbb096aa3f51983cc","modified":1732889622585,"created":1732889585375,"url":"http://localhost:8080/ad","name":"Criar Anuncio","description":"","method":"POST","body":{"mimeType":"application/json","text":"{\n  \"descricao\": \"Baba disponível para cuidar de crianças\",\n  \"preco\": 50.00,\n  \"localidade\": \"São Paulo, SP\",\n  \"usuario_id\": 1\n}\n"},"parameters":[],"headers":[{"name":"Content-Type","value":"application/json"},{"name":"User-Agent","value":"insomnia/10.2.0"}],"authentication":{},"metaSortKey":-1732889585375,"isPrivate":false,"pathParameters":[],"settingStoreCookies":true,"settingSendCookies":true,"settingDisableRenderRequestBody":false,"settingEncodeUrl":true,"settingRebuildPath":true,"settingFollowRedirects":"global","_type":"request"},{"_id":"req_f2dc96bc93c74353a0612653bb615686","parentId":"wrk_f646fb5ab48c4a0dbb096aa3f51983cc","modified":1732887829038,"created":1732887774290,"url":"http://localhost:8080/users/login","name":"Login Sucesso","description":"","method":"POST","body":{"mimeType":"application/json","text":"{\n  \"email\": \"ana.souza@example.com\",\n  \"senha\": \"minhasenha123\"\n}\n"},"parameters":[],"headers":[{"name":"Content-Type","value":"application/json"},{"name":"User-Agent","value":"insomnia/10.2.0"}],"authentication":{},"metaSortKey":-1732887774290,"isPrivate":false,"pathParameters":[],"settingStoreCookies":true,"settingSendCookies":true,"settingDisableRenderRequestBody":false,"settingEncodeUrl":true,"settingRebuildPath":true,"settingFollowRedirects":"global","_type":"request"},{"_id":"req_cd0f9b182ea344bea98d3a3e112f695a","parentId":"wrk_f646fb5ab48c4a0dbb096aa3f51983cc","modified":1732887863136,"created":1732887811574,"url":"http://localhost:8080/users/login","name":"Login Fallha","description":"","method":"POST","body":{"mimeType":"application/json","text":"{\n  \"email\": \"ana.souza@example.com\",\n  \"senha\": \"minhasenha12\"\n}\n"},"parameters":[],"headers":[{"name":"Content-Type","value":"application/json"},{"name":"User-Agent","value":"insomnia/10.2.0"}],"authentication":{},"metaSortKey":-1732471178142,"isPrivate":false,"pathParameters":[],"settingStoreCookies":true,"settingSendCookies":true,"settingDisableRenderRequestBody":false,"settingEncodeUrl":true,"settingRebuildPath":true,"settingFollowRedirects":"global","_type":"request"},{"_id":"req_27af7e917a8448388362a6b0542dff08","parentId":"wrk_f646fb5ab48c4a0dbb096aa3f51983cc","modified":1732888426642,"created":1732054581994,"url":"http://localhost:8080/users?email=ana.souza@example.com","name":"Usuário por email","description":"","method":"GET","body":{},"parameters":[],"headers":[{"name":"User-Agent","value":"insomnia/10.1.1"}],"authentication":{},"metaSortKey":-1732054581994,"isPrivate":false,"pathParameters":[],"settingStoreCookies":true,"settingSendCookies":true,"settingDisableRenderRequestBody":false,"settingEncodeUrl":true,"settingRebuildPath":true,"settingFollowRedirects":"global","_type":"request"},{"_id":"req_c0e2406c3b99484ab49c86d40c5680a9","parentId":"wrk_f646fb5ab48c4a0dbb096aa3f51983cc","modified":1732889608428,"created":1731812653763,"url":"http://localhost:8080/babas/2","name":"Deleta Baba","description":"","method":"DELETE","body":{},"parameters":[],"headers":[{"name":"User-Agent","value":"insomnia/10.1.1"}],"authentication":{},"metaSortKey":-1731812653763,"isPrivate":false,"pathParameters":[],"settingStoreCookies":true,"settingSendCookies":true,"settingDisableRenderRequestBody":false,"settingEncodeUrl":true,"settingRebuildPath":true,"settingFollowRedirects":"global","_type":"request"},{"_id":"req_9c5c138d53d04dffbe7b456ad01b2402","parentId":"wrk_f646fb5ab48c4a0dbb096aa3f51983cc","modified":1732888127759,"created":1731812626608,"url":"http://localhost:8080/users","name":"Criar Usuário","description":"","method":"POST","body":{"mimeType":"application/json","text":"{\n  \"nome\": \"Ana Souza\",\n  \"email\": \"ana.souza@example.com\",\n  \"telefone\": \"123456789\",\n  \"senha\": \"minhasenha123\",\n  \"categoria\": \"baba\"\n}"},"parameters":[],"headers":[{"name":"Content-Type","value":"application/json"},{"name":"User-Agent","value":"insomnia/10.1.1"}],"authentication":{},"metaSortKey":-1731812626608,"isPrivate":false,"pathParameters":[],"settingStoreCookies":true,"settingSendCookies":true,"settingDisableRenderRequestBody":false,"settingEncodeUrl":true,"settingRebuildPath":true,"settingFollowRedirects":"global","_type":"request"},{"_id":"env_7edb13baed615df74f552f06ad00b7e2ce7d709b","parentId":"wrk_f646fb5ab48c4a0dbb096aa3f51983cc","modified":1731812601516,"created":1731812601516,"name":"Base Environment","data":{},"dataPropertyOrder":null,"color":null,"isPrivate":false,"metaSortKey":1731812601516,"_type":"environment"},{"_id":"jar_7edb13baed615df74f552f06ad00b7e2ce7d709b","parentId":"wrk_f646fb5ab48c4a0dbb096aa3f51983cc","modified":1731812601517,"created":1731812601517,"name":"Default Jar","cookies":[],"_type":"cookie_jar"}]}